{
  "id": "Fn05QJS0P535",
  "callback_id": "send_email",
  "title": "Send an email",
  "description": "",
  "type": "app",
  "input_parameters": [
    {
      "type": "string",
      "name": "subject",
      "description": "Enter text",
      "title": "Subject",
      "is_required": true
    },
    {
      "type": "string",
      "name": "email_body",
      "description": "Enter text",
      "title": "Email body",
      "is_required": true,
      "long": true
    },
    {
      "type": "array",
      "name": "recipients",
      "description": "Search all people...",
      "title": "Recipients",
      "is_required": false,
      "items": {
        "type": "slack#/types/user_id"
      },
      "default": []
    },
    {
      "type": "array",
      "name": "additional_recipients",
      "description": "Enter email ids",
      "title": "Additional Recipients",
      "is_required": false,
      "hint": "Enter email ids",
      "items": {
        "type": "string"
      },
      "default": []
    },
    {
      "type": "array",
      "name": "cc_recipients",
      "description": "Enter email ids",
      "title": "CC Recipients",
      "is_required": false,
      "hint": "Enter email ids",
      "items": {
        "type": "string"
      },
      "default": []
    },
    {
      "type": "array",
      "name": "bcc_recipients",
      "description": "Enter email ids",
      "title": "BCC Recipients",
      "is_required": false,
      "hint": "Enter email ids",
      "items": {
        "type": "string"
      },
      "default": []
    },
    {
      "type": "slack#/types/credential/oauth2",
      "name": "outlook_email_access_token",
      "description": "Outlook Email Access Token",
      "title": "Outlook Email Access Token",
      "is_required": true,
      "oauth2_provider_key": "email",
      "require_end_user_auth": true
    }
  ],
  "output_parameters": [],
  "category_id": "A05Q22Z3N8P",
  "category_label": "Microsoft Outlook Email",
  "app_id": "A05Q22Z3N8P",
  "date_created": 1693539779,
  "date_released": 0,
  "date_updated": 1719566464,
  "date_deleted": 0,
  "form_enabled": false
}